{
  "bairro_X": "Nova Descoberta",
  "bairro_Y": "Boa Viagem",
  "custo": 21.3,
  "caminho": [
    "Nova Descoberta",
    "Macaxeira",
    "Apipucos",
    "Caxanga",
    "Varzea",
    "Curado",
    "Sancho",
    "Tejipio",
    "Barro",
    "Cohab",
    "Jordao",
    "Boa Viagem"
  ],
  "ruas": [
    "Rua Dantas",
    "Rua Dolcinópolis",
    "Avenida da Recuperação",
    "Rua Rodrigues Ferreira",
    "Rua Historiador Luiz do Nascimento",
    "Rua Orfeu do Carnaval",
    "Avenida Padre Ibiapina",
    "Rua da Esperança",
    "Avenida Engenho Muribeca",
    "Rua Estrela D`Oeste",
    "Giradouro Felipe Camarão"
  ],
  "pesos": [
    2.1,
    2.16,
    1.22,
    2.22,
    2.34,
    2.21,
    1.22,
    2.16,
    1.24,
    2.19,
    2.24
  ]
}